ydoc/__init__.py
ydoc-0.0.0.dist-info/METADATA
ydoc-0.0.0.dist-info/WHEEL
ydoc-0.0.0.dist-info/licenses/LICENSE
ydoc-0.0.0.dist-info/RECORD
