Metadata-Version: 2.4
Name: ydoc
Version: 0.0.0
Summary: A port of Yjs
Project-URL: Homepage, https://github.com/davidbrochart/ydoc
Author-email: David Brochart <david.brochart@gmail.com>
License: The MIT License (MIT)
License-File: LICENSE
Keywords: crdt,yjs
Requires-Python: >=3.9
